{
  "id": "book-now",
  "title": "BookNow",
  "category": "Full-Stack",
  "skills": ["Java", "Spring Boot", "Angular", "NgRx"],
  "lang": {
    "en": {
      "description": "Developing a web-based application that allows customers to schedule appointments with providers and use their services, post a review and automate a ranking of the bests providers."
    },
    "es": {
      "description": "Developing a web-based application that allows customers to schedule appointments with providers and use their services, post a review and automate a ranking of the bests providers."
    }
  },
  "sourceCode": "https://github.com/AlbenBustamante/book-now",
  "liveDemo": "https://booknow1.vercel.app/",
  "status": "IN_PROGRESS"
}
